lhcbdiracx/routers/__init__.py
lhcbdiracx/routers/py.typed
lhcbdiracx/routers/bookkeeping/__init__.py
lhcbdiracx/routers/bookkeeping/access_policy.py
lhcbdiracx/routers/bookkeeping/bookkeeping.py
lhcbdiracx_routers-0.0.7.dist-info/METADATA
lhcbdiracx_routers-0.0.7.dist-info/WHEEL
lhcbdiracx_routers-0.0.7.dist-info/entry_points.txt
lhcbdiracx_routers-0.0.7.dist-info/top_level.txt
lhcbdiracx_routers-0.0.7.dist-info/RECORD
