Metadata-Version: 2.4
Name: lhcbdiracx-routers
Version: 0.0.7
Summary: TODO
License: GPL-3.0-only
Classifier: Intended Audience :: Science/Research
Classifier: License :: OSI Approved :: GNU General Public License v3 (GPLv3)
Classifier: Programming Language :: Python :: 3
Classifier: Topic :: Scientific/Engineering
Classifier: Topic :: System :: Distributed Computing
Requires-Python: >=3.11
Requires-Dist: lhcbdiracx-core
Requires-Dist: lhcbdiracx-db
Requires-Dist: lhcbdiracx-logic
Requires-Dist: diracx-routers==0.0.7
Provides-Extra: testing
Requires-Dist: diracx-testing==0.0.7; extra == "testing"
Requires-Dist: moto[server]; extra == "testing"
Requires-Dist: pytest-httpx; extra == "testing"
Requires-Dist: diracx-routers[types]==0.0.7; extra == "testing"
Provides-Extra: types
Requires-Dist: diracx-routers[testing]==0.0.7; extra == "types"
Requires-Dist: boto3-stubs; extra == "types"
Requires-Dist: types-aiobotocore[essential]; extra == "types"
Requires-Dist: types-aiobotocore-s3; extra == "types"
Requires-Dist: types-cachetools; extra == "types"
Requires-Dist: types-python-dateutil; extra == "types"
Requires-Dist: types-PyYAML; extra == "types"
Requires-Dist: types-requests; extra == "types"
